[{"jawaban":"binatang katak","foto":"binatang-katak.jpg"},{"jawaban":"es jeruk","foto":"es-jeruk.jpg"},{"jawaban":"fokus penelitian","foto":"fokus-penelitian.jpg"},{"jawaban":"formula istimewa","foto":"formula-istimewa.jpg"},{"jawaban":"harga miring","foto":"harga-miring.jpg"},{"jawaban":"ikan asin mantap disajikan bersama sambal terasi","foto":"ikan-asin-mantap-disajikan-bersama-sambal-terasi.jpg"},{"jawaban":"kalender duduk","foto":"kalender-duduk.jpg"},{"jawaban":"lagu keroncong","foto":"lagu-keroncong.jpg"},{"jawaban":"lupa letak","foto":"lupa-letak.jpg"},{"jawaban":"menolong gelandangan","foto":"menolong-gelandangan.jpg"},{"jawaban":"murid teladan","foto":"murid-teladan.jpg"},{"jawaban":"pendidikan dini","foto":"pendidikan-dini.jpg"},{"jawaban":"pramugari memberikan minuman dingin ke penumpang","foto":"pramugari-memberikan-minuman-dingin-ke-penumpang.jpg"},{"jawaban":"sakit amandel","foto":"sakit-amandel.jpg"},{"jawaban":"satelit komunikasi","foto":"satelit-komunikasi.jpg"},{"jawaban":"sepotong kunyit","foto":"sepotong-kunyit.jpg"},{"jawaban":"sepupuku ganteng","foto":"sepupuku-ganteng.jpg"},{"jawaban":"siksa kubur","foto":"siksa-kubur.jpg"},{"jawaban":"susu fermentasi","foto":"susu-fermentasi.jpg"},{"jawaban":"tetesan cairan","foto":"tetesan-cairan.jpg"}]